CHANGELOG.md
LICENSE
iplib3/__init__.py
iplib3/address.py
iplib3/constants/__init__.py
iplib3/constants/address.py
iplib3/constants/ipv4.py
iplib3/constants/ipv6.py
iplib3/constants/port.py
iplib3/constants/subnet.py
iplib3/subnet.py
iplib3/validators.py
py.typed
iplib3-0.2.4.dist-info/LICENSE
iplib3-0.2.4.dist-info/METADATA
iplib3-0.2.4.dist-info/WHEEL
iplib3-0.2.4.dist-info/RECORD
