Metadata-Version: 2.1
Name: iplib3
Version: 0.2.4
Summary: A modern, object-oriented approach to IP addresses.
Home-page: https://pypi.org/project/iplib3/
License: MIT
Keywords: network,networking,ip,ipaddress,address,python3,pathlib
Author: Lari Liuhamo
Author-email: lari.liuhamo+pypi@gmail.com
Maintainer: Lari Liuhamo
Maintainer-email: lari.liuhamo+pypi@gmail.com
Requires-Python: >=3.9.0,<4.0.0
Classifier: Development Status :: 4 - Beta
Classifier: Intended Audience :: Developers
Classifier: Intended Audience :: Information Technology
Classifier: License :: OSI Approved :: MIT License
Classifier: Operating System :: OS Independent
Classifier: Programming Language :: Python :: 3
Classifier: Programming Language :: Python :: 3.9
Classifier: Programming Language :: Python :: 3.10
Classifier: Programming Language :: Python :: 3.11
Classifier: Programming Language :: Python :: 3.12
Classifier: Programming Language :: Python :: 3.8
Classifier: Programming Language :: Python :: Implementation :: CPython
Classifier: Programming Language :: Python :: Implementation :: PyPy
Classifier: Topic :: Internet
Classifier: Topic :: Software Development :: Libraries
Classifier: Typing :: Typed
Project-URL: Changelog, https://github.com/Diapolo10/iplib3/blob/nightly/CHANGELOG.md
Project-URL: Documentation, https://github.com/Diapolo10/iplib3/tree/main/docs
Project-URL: Repository, https://github.com/Diapolo10/iplib3
Project-URL: Source code, https://github.com/Diapolo10/iplib3
Project-URL: Tracker, https://github.com/Diapolo10/iplib3/issues
